accelbyte_py_sdk/api/achievement/__init__.py
accelbyte_py_sdk/api/achievement/errors.py
accelbyte_py_sdk/api/achievement/models/__init__.py
accelbyte_py_sdk/api/achievement/models/models_achievement_order_update_request.py
accelbyte_py_sdk/api/achievement/models/models_achievement_request.py
accelbyte_py_sdk/api/achievement/models/models_achievement_response.py
accelbyte_py_sdk/api/achievement/models/models_achievement_update_request.py
accelbyte_py_sdk/api/achievement/models/models_additional_info.py
accelbyte_py_sdk/api/achievement/models/models_bulk_create_psn_event_response.py
accelbyte_py_sdk/api/achievement/models/models_bulk_create_psn_events.py
accelbyte_py_sdk/api/achievement/models/models_bulk_unlock_achievement_request.py
accelbyte_py_sdk/api/achievement/models/models_bulk_unlock_achievement_response.py
accelbyte_py_sdk/api/achievement/models/models_contributor_response.py
accelbyte_py_sdk/api/achievement/models/models_create_psn_event.py
accelbyte_py_sdk/api/achievement/models/models_error_details.py
accelbyte_py_sdk/api/achievement/models/models_global_achievement_response.py
accelbyte_py_sdk/api/achievement/models/models_icon.py
accelbyte_py_sdk/api/achievement/models/models_paginated_achievement_response.py
accelbyte_py_sdk/api/achievement/models/models_paginated_contributor_response.py
accelbyte_py_sdk/api/achievement/models/models_paginated_global_achievement_response.py
accelbyte_py_sdk/api/achievement/models/models_paginated_tag_response.py
accelbyte_py_sdk/api/achievement/models/models_paginated_user_achievement_response.py
accelbyte_py_sdk/api/achievement/models/models_paginated_user_contribution_response.py
accelbyte_py_sdk/api/achievement/models/models_pagination.py
accelbyte_py_sdk/api/achievement/models/models_psn_event.py
accelbyte_py_sdk/api/achievement/models/models_psn_event_data.py
accelbyte_py_sdk/api/achievement/models/models_psn_event_result.py
accelbyte_py_sdk/api/achievement/models/models_public_achievement_response.py
accelbyte_py_sdk_service_achievement-0.25.0.dist-info/METADATA
accelbyte_py_sdk_service_achievement-0.25.0.dist-info/WHEEL
accelbyte_py_sdk_service_achievement-0.25.0.dist-info/top_level.txt
accelbyte_py_sdk_service_achievement-0.25.0.dist-info/RECORD
