Metadata-Version: 2.4
Name: accelbyte-py-sdk-service-achievement
Version: 0.25.0
Summary: AccelByte Python SDK - AccelByte Gaming Services Achievement Service
Requires-Python: >=3.9
Requires-Dist: accelbyte-py-sdk-core
